{
  "session": "20251206_195343",
  "task": "Create a python file named 'sandbox/utils.py' that contains a function 'get_system_info()' which returns the current OS name.",
  "events": [
    {
      "phase": "info",
      "time": "2025-12-06T19:53:43.360213",
      "message": "Starting task: Create a python file named 'sandbox/utils.py' that contains ..."
    },
    {
      "phase": "parallel",
      "time": "2025-12-06T19:54:00.745093",
      "workers": [
        {
          "id": 2,
          "duration": 9.5,
          "tool": "python_exec",
          "response": "```json\n{\n  \"tool\": \"python_exec\",\n  \"params\": {\n    \"code\": \"import platform; print(platform.system())\"\n  }\n}\n```\nThis Python script, when executed in the sandbox, will print the current operating system name to the console. Note that it uses the 'platform' module which is built-in for Python, so no external tools are required to create this function."
        },
        {
          "id": 0,
          "duration": 10.6,
          "tool": "python_exec",
          "response": "```json\n{\n  \"tool\": \"python_exec\",\n  \"params\": {\n    \"code\": \"import platform\\nprint(platform.system())\"\n  }\n}\n```\nThis Python code will be executed within the sandbox environment. It imports the platform module, which provides a way to access information about the system where the Python interpreter is running, including the OS name. The function `get_system_info()` will then print the current OS"
        },
        {
          "id": 1,
          "duration": 15.8,
          "tool": "python_exec",
          "response": "```json\n{\n  \"tool\": \"python_exec\",\n  \"params\": {\n    \"code\": \"import platform; return platform.system() + '.' + platform.logical_directory()\"\n  }\n}\n```\n\nThis Python script uses the `platform` module to retrieve the current operating system name and constructs a string in the format 'OS NAME'. The `run_command` tool was used to execute this Python code.\n\nTo create the file 'sandbox/utils.py' in the"
        }
      ]
    },
    {
      "phase": "aggregation",
      "time": "2025-12-06T19:54:19.084930",
      "duration": 18.3,
      "response": "Here is the optimal Python file content `sandbox/utils.py` following the most efficient and straightforward approach using the `platform` module, which fulfills the task requirements:\n\n```python\n# sandbox/utils.py\n\nimport platform\n\ndef get_system_info():\n    \"\"\"Returns the current operating system name.\"\"\"\n    return platform.system()\n\n# Alternatively, if a more detailed info is needed, we could combine with directory info:\ndef get_detailed_system_info():\n    \"\"\"Returns a more comprehensive stri"
    },
    {
      "phase": "refine",
      "time": "2025-12-06T19:54:35.329169",
      "iteration": 1,
      "score": 20,
      "feedback": "Refined in 0.0s"
    },
    {
      "phase": "final",
      "time": "2025-12-06T19:54:35.330045",
      "score": 20,
      "total_time": 52.0,
      "response": "Here is the optimal Python file content `sandbox/utils.py` following the most efficient and straightforward approach using the `platform` module, which fulfills the task requirements:\n\n```python\n# sandbox/utils.py\n\nimport platform\n\ndef get_system_info():\n    \"\"\"Returns the current operating system name.\"\"\"\n    return platform.system()\n\n# Alternatively, if a more detailed info is needed, we could combine with directory info:\ndef get_detailed_system_info():\n    \"\"\"Returns a more comprehensive string containing OS name and directory.\"\"\"\n    os_name = platform.system()\n    log_dir = platform.logic"
    }
  ]
}