{
  "session_start": "2025-12-10T01:34:25.303131",
  "last_updated": "2025-12-10T02:31:43.992785",
  "events": [
    {
      "time": "2025-12-10T01:34:35.902036",
      "type": "task_start",
      "details": {
        "session_id": "auto_145_1765330475",
        "task": "Category: LIST\nTask: Implement `find_max_subarray` - Given an array of integers, return the contiguo"
      }
    },
    {
      "time": "2025-12-10T01:46:12.318451",
      "type": "task_complete",
      "details": {
        "session_id": "auto_145_1765330475",
        "score": 23,
        "duration": 696.4163541793823,
        "verified": false,
        "skipped_refine": false
      }
    },
    {
      "time": "2025-12-10T01:46:27.018173",
      "type": "task_start",
      "details": {
        "session_id": "auto_146_1765331187",
        "task": "Category: LIST\nTask: Implement `find_max_sublist(nums)` that finds and returns the contiguous sublis"
      }
    },
    {
      "time": "2025-12-10T01:51:33.653470",
      "type": "task_complete",
      "details": {
        "session_id": "auto_146_1765331187",
        "score": 23,
        "duration": 306.6352586746216,
        "verified": false,
        "skipped_refine": false
      }
    },
    {
      "time": "2025-12-10T01:51:50.841168",
      "type": "task_start",
      "details": {
        "session_id": "auto_147_1765331510",
        "task": "Category: MATH\nTask: Implement `solve(input)` that calculates the nth Fibonacci number using matrix "
      }
    },
    {
      "time": "2025-12-10T01:53:23.847479",
      "type": "task_complete",
      "details": {
        "session_id": "auto_147_1765331510",
        "score": 18,
        "duration": 93.00627112388611,
        "verified": false,
        "skipped_refine": false
      }
    },
    {
      "time": "2025-12-10T01:53:40.527164",
      "type": "task_start",
      "details": {
        "session_id": "auto_148_1765331620",
        "task": "Category: LIST\nTask: Implement `find_max_subarray` - Given an array of integers, find the contiguous"
      }
    },
    {
      "time": "2025-12-10T02:04:06.562495",
      "type": "task_complete",
      "details": {
        "session_id": "auto_148_1765331620",
        "score": 23,
        "duration": 626.0352885723114,
        "verified": false,
        "skipped_refine": false
      }
    },
    {
      "time": "2025-12-10T02:04:23.249174",
      "type": "task_start",
      "details": {
        "session_id": "auto_149_1765332263",
        "task": "Category: LIST\nTask: Implement `find_max_subarray` - Find the contiguous subarray within a given lis"
      }
    },
    {
      "time": "2025-12-10T02:05:14.547602",
      "type": "task_complete",
      "details": {
        "session_id": "auto_149_1765332263",
        "score": 22,
        "duration": 51.2983934879303,
        "verified": false,
        "skipped_refine": false
      }
    },
    {
      "time": "2025-12-10T02:05:41.271218",
      "type": "task_start",
      "details": {
        "session_id": "auto_150_1765332341",
        "task": "Category: LIST\nTask: Implement `find_max_subsequence(input)` that finds the longest contiguous subse"
      }
    },
    {
      "time": "2025-12-10T02:07:24.729249",
      "type": "task_complete",
      "details": {
        "session_id": "auto_150_1765332341",
        "score": 18,
        "duration": 103.45799446105957,
        "verified": false,
        "skipped_refine": false
      }
    },
    {
      "time": "2025-12-10T02:13:15.787596",
      "type": "task_start",
      "details": {
        "session_id": "auto_151_1765332795",
        "task": "Category: LIST\nTask: Implement `find_max_subarray` - Given an array of integers, find the contiguous"
      }
    },
    {
      "time": "2025-12-10T02:23:08.786849",
      "type": "task_complete",
      "details": {
        "session_id": "auto_151_1765332795",
        "score": 3,
        "duration": 592.9991700649261,
        "verified": false,
        "skipped_refine": false
      }
    },
    {
      "time": "2025-12-10T02:23:27.047948",
      "type": "task_start",
      "details": {
        "session_id": "auto_152_1765333407",
        "task": "Category: LIST\nTask: Implement `find_max_subarray` function that finds the contiguous subarray withi"
      }
    },
    {
      "time": "2025-12-10T02:31:43.992773",
      "type": "task_complete",
      "details": {
        "session_id": "auto_152_1765333407",
        "score": 23,
        "duration": 496.944748878479,
        "verified": false,
        "skipped_refine": false
      }
    }
  ],
  "metrics": {
    "scores": [
      23,
      23,
      18,
      23,
      22,
      18,
      3
    ],
    "durations": [
      696.4163541793823,
      306.6352586746216,
      93.00627112388611,
      626.0352885723114,
      51.2983934879303,
      103.45799446105957,
      592.9991700649261
    ],
    "verified_count": [
      0,
      0,
      0,
      0,
      0,
      0,
      0
    ],
    "skip_count": [
      0,
      0,
      0,
      0,
      0,
      0,
      0
    ]
  },
  "errors": []
}